get_unicode_multiline_input_with_editor.py
get_unicode_multiline_input_with_editor-0.1.0a1.dist-info/licenses/LICENSE
get_unicode_multiline_input_with_editor-0.1.0a1.dist-info/METADATA
get_unicode_multiline_input_with_editor-0.1.0a1.dist-info/WHEEL
get_unicode_multiline_input_with_editor-0.1.0a1.dist-info/top_level.txt
get_unicode_multiline_input_with_editor-0.1.0a1.dist-info/RECORD
