Metadata-Version: 2.4
Name: get-unicode-multiline-input-with-editor
Version: 0.1.0a1
Summary: Opens `$EDITOR` to get multi-line input as a list of Unicode strings, just like what `git commit` does.
Author-email: Jifeng Wu <jifengwu2k@gmail.com>
License-Expression: MIT
Project-URL: Homepage, https://github.com/jifengwu2k/get-unicode-multiline-input-with-editor
Project-URL: Bug Tracker, https://github.com/jifengwu2k/get-unicode-multiline-input-with-editor/issues
Classifier: Programming Language :: Python :: 2
Classifier: Programming Language :: Python :: 3
Classifier: Operating System :: OS Independent
Requires-Python: >=2
License-File: LICENSE
Requires-Dist: ctypes-unicode-proclaunch
Requires-Dist: get-unicode-arguments-to-launch-editor
Requires-Dist: typing; python_version < "3.5"
Dynamic: license-file
